sagephys/__init__.py
sagephys/classical_mechanics/__init__.py
sagephys/classical_mechanics/_newtonian.py
sagephys/py.typed
sage_physics-0.1.0.dist-info/WHEEL
sage_physics-0.1.0.dist-info/METADATA
sage_physics-0.1.0.dist-info/licenses/LICENSE
sage_physics-0.1.0.dist-info/RECORD
