Metadata-Version: 2.1
Name: sage-physics
Version: 0.1.0
Summary: A Python package to create and simulate physics models.
License: MIT
Author-email: Georgios Douzas <gdouzas@icloud.com>
Requires-Python: >=3.9, <3.12
Classifier: Development Status :: 4 - Beta
Classifier: Intended Audience :: Developers
Classifier: Programming Language :: Python
Classifier: Programming Language :: Python :: 3
Classifier: Programming Language :: Python :: 3 :: Only
Classifier: Programming Language :: Python :: 3.11
Classifier: Topic :: Documentation
Classifier: Topic :: Software Development
Classifier: Topic :: Utilities
Classifier: Typing :: Typed
Project-URL: Changelog, https://georgedouzas.github.io/sage-physics/changelog
Project-URL: Discussions, https://github.com/georgedouzas/sage-physics/discussions
Project-URL: Documentation, https://georgedouzas.github.io/sage-physics
Project-URL: Funding, https://github.com/sponsors/georgedouzas
Project-URL: Gitter, https://gitter.im/sage-physics/community
Project-URL: Homepage, https://georgedouzas.github.io/sage-physics
Project-URL: Issues, https://github.com/georgedouzas/sage-physics/issues
Project-URL: Repository, https://github.com/georgedouzas/sage-physics
